[
    {
        "id": 1,
        "question": "Pythonの創設者は誰ですか？",
        "choices": ["ケン・トンプソン", "デニス・リッチー", "ジェームズ・ゴスリン", "グイド・ヴァン・ロッサム", "スティーブ・ジョブズ"],
        "answer": 4,
        "points": 2
    },
    {
        "id": 2,
        "question": "HTMLでページのタイトルを指定するタグは何ですか？",
        "choices": ["選択肢1", "選択肢2", "選択肢3", "選択肢4", "選択肢5"],
        "answer": 1,
        "points": 2
    },
    {
        "id": 3,
        "question": "これはテスト問題です、これはテスト問題です、これはテスト問題です、これはテスト問題です、これはテスト問題です、これはテスト問題です、これはテスト問題です、これはテスト問題です、これはテスト問題です、これはテスト問題です、これはテスト問題です、これはテスト問題です、これはテスト問題です、これはテスト問題です、これはテスト問題です、これはテスト問題です、これはテスト問題です",
        "choices": ["選択肢1", "選択肢2", "選択肢3", "選択肢4", "選択肢5"],
        "answer": 1,
        "points": 2
    },
    {
        "id": 4,
        "question": "これはテスト問題です",
        "choices": ["選択肢1", "選択肢2", "選択肢3", "選択肢4", "選択肢5"],
        "answer": 1,
        "points": 2
    },
    {
        "id": 5,
        "question": "これはテスト問題です",
        "choices": ["選択肢1", "選択肢2", "選択肢3", "選択肢4", "選択肢5"],
        "answer": 1,
        "points": 2
    },
    {
        "id": 6,
        "question": "これはテスト問題です",
        "choices": ["選択肢1", "選択肢2", "選択肢3", "選択肢4", "選択肢5"],
        "answer": 1,
        "points": 2
    },
    {
        "id": 7,
        "question": "これはテスト問題です",
        "choices": ["選択肢1", "選択肢2", "選択肢3", "選択肢4", "選択肢5"],
        "answer": 1,
        "points": 2
    },
    {
        "id": 8,
        "question": "これはテスト問題です",
        "choices": ["選択肢1", "選択肢2", "選択肢3", "選択肢4", "選択肢5"],
        "answer": 1,
        "points": 2
    },
    {
        "id": 9,
        "question": "これはテスト問題です",
        "choices": ["選択肢1", "選択肢2", "選択肢3", "選択肢4", "選択肢5"],
        "answer": 1,
        "points": 2
    },
    {
        "id": 10,
        "question": "これはテスト問題です",
        "choices": ["選択肢1", "選択肢2", "選択肢3", "選択肢4", "選択肢5"],
        "answer": 1,
        "points": 2
    }
]